setup.cfg
setup.py
cursesinquirer/__init__.py
cursesinquirer/builtins.py
cursesinquirer/question.py
cursesinquirer.egg-info/PKG-INFO
cursesinquirer.egg-info/SOURCES.txt
cursesinquirer.egg-info/dependency_links.txt
cursesinquirer.egg-info/top_level.txt