Metadata-Version: 1.1
Name: cursesinquirer
Version: 0.1.1
Summary: A library to create curses based CLIs
Home-page: https://github.com/kemichal/cursesinquirer
Author: Robert Andersson
Author-email: kemichal@gmail.com
License: MIT
Keywords: curses,inquirer,questionnaire,cli,terminal,development
Platform: UNKNOWN
Classifier: Development Status :: 4 - Beta
Classifier: Intended Audience :: Developers
Classifier: Programming Language :: Python :: 3.5
Classifier: Environment :: Console
Classifier: Environment :: Console :: Curses
Classifier: License :: OSI Approved :: MIT License
Classifier: Operating System :: POSIX :: Linux
